zhesp/__init__.py
zhesp/console.py
zhesp2-2.3.4.dist-info/METADATA
zhesp2-2.3.4.dist-info/WHEEL
zhesp2-2.3.4.dist-info/entry_points.txt
zhesp2-2.3.4.dist-info/top_level.txt
zhesp2-2.3.4.dist-info/RECORD
