Metadata-Version: 2.4
Name: zhesp2
Version: 2.3.4
Summary: Z-HESP2: Zero's Hash Encryption Secure Protocol (v2)
Author: ZeroDay
Classifier: Programming Language :: Python :: 3
Classifier: Operating System :: OS Independent
Classifier: License :: OSI Approved :: MIT License
Classifier: Topic :: Security :: Cryptography
Requires-Python: >=3.10
Requires-Dist: argon2-cffi
Requires-Dist: pycryptodome
Dynamic: author
Dynamic: classifier
Dynamic: requires-dist
Dynamic: requires-python
Dynamic: summary
